agentsociety_community/__init__.py
agentsociety_community/agents/__init__.py
agentsociety_community/agents/citizens/__init__.py
agentsociety_community/agents/citizens/bdsc2025_track_one_envambassador/__init__.py
agentsociety_community/agents/citizens/bdsc2025_track_one_envambassador/baseline.py
agentsociety_community/agents/citizens/bdsc2025_track_one_envambassador/defaults.py
agentsociety_community/agents/citizens/bdsc2025_track_one_envambassador/embagentbase.py
agentsociety_community/agents/citizens/bdsc2025_track_one_envambassador/fundmanager.py
agentsociety_community/agents/citizens/bdsc2025_track_one_envambassador/sharing_params.py
agentsociety_community/agents/citizens/bdsc2025_track_one_envambassador/tools/__init__.py
agentsociety_community/agents/citizens/bdsc2025_track_one_envambassador/tools/announcement.py
agentsociety_community/agents/citizens/bdsc2025_track_one_envambassador/tools/communication.py
agentsociety_community/agents/citizens/bdsc2025_track_one_envambassador/tools/message_probe.py
agentsociety_community/agents/citizens/bdsc2025_track_one_envambassador/tools/poster.py
agentsociety_community/agents/citizens/bdsc2025_track_one_envambassador/tools/sense.py
agentsociety_community/agents/citizens/bdsc2025_track_one_envambassador/tools/utils.py
agentsociety_community/agents/citizens/bdsc2025_track_one_envcitizen/__init__.py
agentsociety_community/agents/citizens/bdsc2025_track_one_envcitizen/track_one_envcitizen.py
agentsociety_community/agents/citizens/bdsc2025_track_one_envcitizen/blocks/__init__.py
agentsociety_community/agents/citizens/bdsc2025_track_one_envcitizen/blocks/cognition_block.py
agentsociety_community/agents/citizens/bdsc2025_track_one_envcitizen/blocks/economy_block.py
agentsociety_community/agents/citizens/bdsc2025_track_one_envcitizen/blocks/mobility_block.py
agentsociety_community/agents/citizens/bdsc2025_track_one_envcitizen/blocks/needs_block.py
agentsociety_community-0.3.3.dist-info/METADATA
agentsociety_community-0.3.3.dist-info/WHEEL
agentsociety_community-0.3.3.dist-info/licenses/LICENSE
agentsociety_community-0.3.3.dist-info/RECORD
