Metadata-Version: 2.4
Name: agentsociety-community
Version: 0.3.3
Summary: A community library for customizing agent/block for AgentSociety
Project-URL: Homepage, https://github.com/tsinghua-fib-lab/agentsociety-community
Project-URL: Repository, https://github.com/tsinghua-fib-lab/agentsociety-community.git
Project-URL: Issues, https://github.com/tsinghua-fib-lab/agentsociety-community/issues
Author-email: Jun Zhang <zhangjun990222@gmail.com>
License:                                  Apache License
License-File: LICENSE
Classifier: Operating System :: MacOS :: MacOS X
Classifier: Operating System :: POSIX :: Linux
Classifier: Programming Language :: Python :: 3
Requires-Python: >=3.11
Requires-Dist: agentsociety>=1.5.0a9
